glasskit/__init__.py
glasskit/__main__.py
glasskit/api.py
glasskit/base.py
glasskit/cache.py
glasskit/context.py
glasskit/controller.py
glasskit/errors.py
glasskit/json.py
glasskit/profilers.py
glasskit/sessions.py
glasskit/utils.py
glasskit/commands/__init__.py
glasskit/commands/index.py
glasskit/commands/run.py
glasskit/commands/shell.py
glasskit/commands/tasks.py
glasskit/commands/test.py
glasskit/idconnect/__init__.py
glasskit/idconnect/config.py
glasskit/idconnect/facebook.py
glasskit/idconnect/github.py
glasskit/idconnect/provider.py
glasskit/idconnect/yandex.py
glasskit/project_templates/.shellrc.py
glasskit/project_templates/glass.py.tmpl
glasskit/project_templates/requirements.txt
glasskit/project_templates/wsgi.py.tmpl
glasskit/project_templates/__appname__/__init__.py
glasskit/project_templates/__appname__/app.py
glasskit/project_templates/__appname__/controllers/__init__.py
glasskit/project_templates/__appname__/models/__init__.py
glasskit/project_templates/__appname__/tasks/__init__.py
glasskit/project_templates/__appname__/tasks/worker.py
glasskit/project_templates/commands/__init__.py
glasskit/project_templates/config/development.py.tmpl
glasskit/project_templates/config/production.py.tmpl
glasskit/project_templates/config/testing.py.tmpl
glasskit/queue/__init__.py
glasskit/queue/base_queue.py
glasskit/queue/dummy_queue.py
glasskit/queue/mongo_queue.py
glasskit/queue/redis_queue.py
glasskit/queue/task.py
glasskit/queue/worker.py
glasskit/tests/__init__.py
glasskit/tests/__main__.py
glasskit/tests/mongo_mock_test.py
glasskit/tests/test_base_model.py
glasskit/tests/test_sharded_model.py
glasskit/tests/test_storable_model.py
glasskit/tests/test_submodel.py
glasskit/tests/test_validators.py
glasskit/unit_templates/controller.py.tmpl
glasskit/unit_templates/model.py.tmpl
glasskit/unit_templates/task.py.tmpl
glasskit/uorm/__init__.py
glasskit/uorm/db.py
glasskit/uorm/errors.py
glasskit/uorm/utils.py
glasskit/uorm/models/__init__.py
glasskit-3.11.12.dist-info/METADATA
glasskit-3.11.12.dist-info/WHEEL
glasskit-3.11.12.dist-info/entry_points.txt
glasskit-3.11.12.dist-info/top_level.txt
glasskit-3.11.12.dist-info/RECORD
